langchain_hedera/__init__.py
langchain_hedera/agents/__init__.py
langchain_hedera/agents/defi_agent.py
langchain_hedera/agents/portfolio_agent.py
langchain_hedera/agents/trading_agent.py
langchain_hedera/chains/__init__.py
langchain_hedera/chains/arbitrage_chain.py
langchain_hedera/chains/defi_analysis_chain.py
langchain_hedera/tools/__init__.py
langchain_hedera/tools/bonzo_tools.py
langchain_hedera/tools/hedera_tools.py
langchain_hedera/tools/saucerswap_tools.py
langchain_hedera/utils/__init__.py
langchain_hedera/utils/config.py
langchain_hedera/utils/helpers.py
langchain_hedera-0.1.0.dist-info/licenses/LICENSE
langchain_hedera-0.1.0.dist-info/METADATA
langchain_hedera-0.1.0.dist-info/WHEEL
langchain_hedera-0.1.0.dist-info/top_level.txt
langchain_hedera-0.1.0.dist-info/RECORD
