Metadata-Version: 2.4
Name: langchain-hedera
Version: 0.1.0
Summary: LangChain integration for Hedera DeFi analytics with intelligent agents and tools
Home-page: https://github.com/samthedataman/langchain-hedera
Author: Sam Savage
Author-email: Sam Savage <admin@quantdefi.ai>
License: MIT
Project-URL: Homepage, https://github.com/samthedataman/langchain-hedera
Project-URL: Repository, https://github.com/samthedataman/langchain-hedera
Project-URL: Issues, https://github.com/samthedataman/langchain-hedera/issues
Project-URL: Documentation, https://langchain-hedera.readthedocs.io
Keywords: langchain,hedera,defi,blockchain,analytics,agents,llm,cryptocurrency,saucerswap,bonzo-finance
Classifier: Development Status :: 3 - Alpha
Classifier: Intended Audience :: Developers
Classifier: Topic :: Software Development :: Libraries :: Python Modules
Classifier: Topic :: Scientific/Engineering :: Artificial Intelligence
Classifier: License :: OSI Approved :: MIT License
Classifier: Programming Language :: Python :: 3
Classifier: Programming Language :: Python :: 3.8
Classifier: Programming Language :: Python :: 3.9
Classifier: Programming Language :: Python :: 3.10
Classifier: Programming Language :: Python :: 3.11
Classifier: Operating System :: OS Independent
Requires-Python: >=3.8
License-File: LICENSE
Requires-Dist: langchain>=0.1.0
Requires-Dist: langchain-core>=0.1.0
Requires-Dist: langchain-community>=0.0.10
Requires-Dist: langchain-openai>=0.0.5
Requires-Dist: pydantic>=2.0.0
Requires-Dist: requests>=2.28.0
Requires-Dist: pandas>=1.5.0
Requires-Dist: numpy>=1.21.0
Requires-Dist: python-dateutil>=2.8.0
Requires-Dist: typing-extensions>=4.0.0
Requires-Dist: hedera-defi>=0.3.0
Provides-Extra: dev
Requires-Dist: pytest>=7.0.0; extra == "dev"
Requires-Dist: black>=22.0.0; extra == "dev"
Requires-Dist: flake8>=4.0.0; extra == "dev"
Requires-Dist: mypy>=0.950; extra == "dev"
Requires-Dist: jupyter>=1.0.0; extra == "dev"
Requires-Dist: langchain-openai>=0.0.5; extra == "dev"
Requires-Dist: python-dotenv>=1.0.0; extra == "dev"
Provides-Extra: examples
Requires-Dist: langchain-openai>=0.0.5; extra == "examples"
Requires-Dist: jupyter>=1.0.0; extra == "examples"
Requires-Dist: python-dotenv>=1.0.0; extra == "examples"
Requires-Dist: streamlit>=1.28.0; extra == "examples"
Requires-Dist: plotly>=5.0.0; extra == "examples"
Dynamic: author
Dynamic: home-page
Dynamic: license-file
Dynamic: requires-python
